{
    "version": "0.4",
    "title": "Contact Us",
    "type": "page",
    "page_settings": [],
    "content": [
        {
            "id": "5d8a27b6",
            "elType": "section",
            "settings": {
                "content_width": "boxed",
                "gap": "extended",
                "padding": {
                    "unit": "px",
                    "top": "48",
                    "right": "0",
                    "bottom": "48",
                    "left": "0",
                    "isLinked": false
                }
            },
            "elements": [
                {
                    "id": "0dcf938d",
                    "elType": "column",
                    "settings": {
                        "_column_size": 100
                    },
                    "elements": [
                        {
                            "id": "cc072257",
                            "elType": "widget",
                            "widgetType": "gms-contact-form",
                            "settings": {
                                "eyebrow": "Contact Us",
                                "title": "Ready to build trust-led pipeline?",
                                "description": "Let\u2019s build a stronger pipeline for your security business that is secure, scalable, and measurable.",
                                "email": "hello@growmysecuritycompany.com",
                                "phone": "+1 (623) 282-1778"
                            },
                            "elements": []
                        }
                    ]
                }
            ]
        }
    ]
}